flagbase/__init__.py
flagbase/client.py
flagbase/config.py
flagbase/context.py
flagbase/events.py
flagbase/identity.py
flagbase/store.py
flagbase/types.py
flagbase/version.py
flagbase/evaluation/__init__.py
flagbase/evaluation/bucket.py
flagbase/evaluation/engine.py
flagbase/evaluation/evaluation.py
flagbase/evaluation/matcher.py
flagbase/model/__init__.py
flagbase/model/reason.py
flagbase/model/variation.py
flagbase/transport/__init__.py
flagbase/transport/poller.py
flagbase/transport/transport.py
flagbase/util/__init__.py
flagbase/util/hashutil.py
flagbase-0.0.8.dist-info/METADATA
flagbase-0.0.8.dist-info/WHEEL
flagbase-0.0.8.dist-info/top_level.txt
flagbase-0.0.8.dist-info/RECORD
