Metadata-Version: 2.1
Name: flagbase
Version: 0.0.8
Summary: Flagbase Python Server SDK
Home-page: https://flagbase.com
Author: The Flagbase Team
Author-email: cjoy@flagbase.com
Classifier: Development Status :: 3 - Alpha
Classifier: Intended Audience :: Developers
Classifier: License :: OSI Approved :: MIT License
Classifier: Programming Language :: Python
Classifier: Programming Language :: Python :: 3
Classifier: Programming Language :: Python :: 3.6
Classifier: Programming Language :: Python :: 3.7
Classifier: Programming Language :: Python :: 3.8
Classifier: Programming Language :: Python :: 3.9
Classifier: Topic :: Software Development :: Libraries
